<mvc:View height="100%"
	controllerName="Cloud_Group1_ProjectCloud_Group1_Project.controller.estimate.estlookup"
	xmlns:l="sap.ui.layout" xmlns:f="sap.ui.layout.form"
	xmlns:core="sap.ui.core" xmlns:mvc="sap.ui.core.mvc" xmlns="sap.m">
	<Page title="견적서 상세 화면" showNavButton="true"
		navButtonPress="goBack">
		<headerContent>
			<Button type="Accept" text="계약서 등록" id="button"
				press=".onShow" />
		</headerContent>

		<content>
			<ObjectHeader title="견적번호" backgroundDesign="Solid">
				<attributes>
					<ObjectAttribute id="" title="유효 여부" text="" state="Success" />
					<ObjectAttribute title="견적일자" text="2019.10.31" />
					<ObjectAttribute title="품명" text="컴퓨터" />
					<ObjectAttribute title="총 합계 금액" text="{sum>/sum}" />
				</attributes>
			</ObjectHeader>
<!-- 						<VBox class="sapUiSmallMargin"> -->
							<f:SimpleForm id="Form1" editable="false"
								layout="ResponsiveGridLayout" title="공급업체 설명" labelSpanXL="4"
								labelSpanL="3" labelSpanM="12" labelSpanS="12"
								adjustLabelSpan="false" emptySpanXL="0" emptySpanL="0"
								emptySpanM="0" emptySpanS="0" columnsXL="2" columnsL="2"
								columnsM="1" singleContainerFullSize="false" class="white">
								<f:content>
									<core:Title text="" />
									<Label text="공급업체명" />
									<Text text="1100" />
									<Label text="공급업체 코드" />
									<Text text="452" />
									<Label text="사업자 등록번호" />
									<Text text="452" />
									<Label text="공급업체 주소" />
									<Text text="452" />
									<Label text="대표자" />
									<Text text="99999999" />
									<Label text="" />
									<core:Title text="" />
									<Label text="업태" />
									<Text text="452" />
									<Label text="종목" />
									<Text text="452" />
									<Label text="이메일" />
									<Text text="452" />
									<Label text="제조사" />
									<Text text="452" />
									<Label text="" />
								</f:content>
							</f:SimpleForm>
									<f:SimpleForm title="제품 설명" layout="ResponsiveGridLayout" labelSpanXL="4"
								labelSpanL="3" labelSpanM="12" labelSpanS="12"
								adjustLabelSpan="false" emptySpanXL="0" emptySpanL="0"
								emptySpanM="0" emptySpanS="0" columnsXL="2" columnsL="2"
								columnsM="1" singleContainerFullSize="false" class="white">
									</f:SimpleForm>
									<Table items="{estlist>/data}" id="esttable"
										inset="false">
										<columns>
											<Column>
												<Text text="대분류 코드" />
											</Column>
											<Column>
												<Text text="중분류 코드" />
											</Column>
											<Column>
												<Text text="제품명" />
											</Column>
											<Column>
												<Text text="제품코드" />
											</Column>
											<Column>
												<Text text="수량" />
											</Column>
											<Column>
												<Text text="단가" />
											</Column>
											<Column>
												<Text text="공급업체코드" />
											</Column>
											<Column>
												<Text text="수량" />
											</Column>
											<Column>
												<Text text="단가" />
											</Column>
											<Column>
												<Text text="총금액" />
											</Column>
											<Column>
												<Text text="금액단위" />
											</Column>
										</columns>
										<items>
											<ColumnListItem>
												<cells>
													<!-- <ObjectIdentifier title="{/data}" /> text="{ProductId}" -->
													<Text text="{estlist>EstNo}" />
													<Text text="{estlist>EstAva}" />
													<Text text="{estlist>EstCat1}" />
													<Text text="{estlist>EstCat2}" />
													<Text text="{estlist>EstCat3}" />
													<Text text="{estlist>EstVname}" />
													<Text text="{estlist>EstVcode}" />
													<Text text="{estlist>EstAmt}" />
													<Text text="{estlist>EstPrice}" />
													<Text text="{estlist>EstTotal}" />
													<Text text="{estlist>EstCuky}" />
												</cells>
											</ColumnListItem>
										</items>
									</Table>
<!-- 								</f:content> -->
<!-- 							</f:SimpleForm> -->
<!-- 						</VBox>  -->
			<IconTabBar expanded=""
				class="sapUiSmallMarginBottom sapUiResponsiveContentPadding">
				<items>
					<IconTabFilter text="견적서 상세 조회">
	
					</IconTabFilter>
				</items>
			</IconTabBar>
		</content>
	</Page>
</mvc:View>